Metadata-Version: 1.0
Name: git-lambda
Version: 1.1.2
Summary: A compiled binary of git for use in AWS Lambda
Home-page: https://github.com/bcongdon/git_lambda
Author: Benjamin Congdon
Author-email: me@bcon.gdn
License: UNKNOWN
Platform: UNKNOWN
